README.md
setup.py
bmmflux/__init__.py
bmmflux/read_bmmflux.py
btmm_process/__init__.py
btmm_process/calibrate.py
btmm_process/dtsarch.py
btmm_process/labeler.py
btmm_process/readDTS.py
btmm_process.egg-info/PKG-INFO
btmm_process.egg-info/SOURCES.txt
btmm_process.egg-info/dependency_links.txt
btmm_process.egg-info/not-zip-safe
btmm_process.egg-info/requires.txt
btmm_process.egg-info/top_level.txt