Metadata-Version: 1.0
Name: btmm-process
Version: 0.1
Summary: Processing of meteorological FODS data.
Home-page: UNKNOWN
Author: Karl Lapo and Anita Freundorfer
Author-email: karl-lapo@uni-bayreuth.de
License: MIT
Platform: UNKNOWN
